README.md
setup.py
datalang/__init__.py
datalang/main.py
datalang.egg-info/PKG-INFO
datalang.egg-info/SOURCES.txt
datalang.egg-info/dependency_links.txt
datalang.egg-info/top_level.txt