Metadata-Version: 2.1
Name: datalang
Version: 1.0.6
Summary: A parser for Datalang.
Home-page: UNKNOWN
Author: Sendokame
License: UNKNOWN
Platform: UNKNOWN
